setup.py
lama/__init__.py
lama/config.py
lama/upload.py
lama.egg-info/PKG-INFO
lama.egg-info/SOURCES.txt
lama.egg-info/dependency_links.txt
lama.egg-info/entry_points.txt
lama.egg-info/requires.txt
lama.egg-info/top_level.txt