Metadata-Version: 1.0
Name: lama
Version: 0.1
Summary: a tool to take screenshots and upload to imgur from command line.
Home-page: http://github.com/emre/lama
Author: Emre Yilmaz
Author-email: mail@emreyilmaz.me
License: MIT
Platform: UNKNOWN
